my_python_rocksdb/setup.py
my_python_rocksdb/rocksdb/__init__.py
my_python_rocksdb/rocksdb/errors.py
my_python_rocksdb/rocksdb/interfaces.py
my_python_rocksdb/rocksdb/merge_operators.py
my_python_rocksdb/rocksdb/tests/__init__.py
my_python_rocksdb/rocksdb/tests/test_db.py
my_python_rocksdb/rocksdb/tests/test_memtable.py
my_python_rocksdb/rocksdb/tests/test_options.py
my_python_rocksdb-0.7.0.dist-info/LICENCE
my_python_rocksdb-0.7.0.dist-info/METADATA
my_python_rocksdb-0.7.0.dist-info/WHEEL
my_python_rocksdb-0.7.0.dist-info/top_level.txt
my_python_rocksdb-0.7.0.dist-info/RECORD
