Metadata-Version: 2.1
Name: my_python_rocksdb
Version: 0.7.0
Summary: A alternative rocksdb package
Author-email: Daniel Siegmann <dsiegmann@bluewin.ch>
Project-URL: Homepage, https://github.com/chainlaboratory
Classifier: Programming Language :: Python :: 3
Classifier: License :: OSI Approved :: MIT License
Classifier: Operating System :: OS Independent
Requires-Python: >=3.8
License-File: LICENCE
